LICENSE
MANIFEST.in
README.md
README.rst
setup.py
doc/migen_logo.png
doc/migen_logo.svg
migen/__init__.py
migen.egg-info/PKG-INFO
migen.egg-info/SOURCES.txt
migen.egg-info/dependency_links.txt
migen.egg-info/requires.txt
migen.egg-info/top_level.txt
migen/build/__init__.py
migen/build/fpgalink_programmer.py
migen/build/generic_platform.py
migen/build/generic_programmer.py
migen/build/openocd.py
migen/build/tools.py
migen/build/altera/__init__.py
migen/build/altera/common.py
migen/build/altera/platform.py
migen/build/altera/programmer.py
migen/build/altera/quartus.py
migen/build/lattice/__init__.py
migen/build/lattice/common.py
migen/build/lattice/diamond.py
migen/build/lattice/icestorm.py
migen/build/lattice/platform.py
migen/build/lattice/programmer.py
migen/build/lattice/trellis.py
migen/build/platforms/__init__.py
migen/build/platforms/afc3v1.py
migen/build/platforms/apf27.py
migen/build/platforms/apf51.py
migen/build/platforms/apf6sp.py
migen/build/platforms/arty_a7.py
migen/build/platforms/arty_s7.py
migen/build/platforms/de0cv.py
migen/build/platforms/de0nano.py
migen/build/platforms/de0nanosoc.py
migen/build/platforms/de10lite.py
migen/build/platforms/ice40_hx1k_blink_evn.py
migen/build/platforms/ice40_hx8k_b_evn.py
migen/build/platforms/ice40_up5k_b_evn.py
migen/build/platforms/icebreaker.py
migen/build/platforms/icestick.py
migen/build/platforms/kc705.py
migen/build/platforms/kcu105.py
migen/build/platforms/lx9_microboard.py
migen/build/platforms/m1.py
migen/build/platforms/max1000.py
migen/build/platforms/mercury.py
migen/build/platforms/mimasv2.py
migen/build/platforms/minispartan6.py
migen/build/platforms/mixxeo.py
migen/build/platforms/ml605.py
migen/build/platforms/mystorm_blackice.py
migen/build/platforms/mystorm_blackice_ii.py
migen/build/platforms/papilio_pro.py
migen/build/platforms/pipistrello.py
migen/build/platforms/qm_xc6slx16_sdram.py
migen/build/platforms/rhino.py
migen/build/platforms/tinyfpga_a.py
migen/build/platforms/tinyfpga_b.py
migen/build/platforms/tinyfpga_bx.py
migen/build/platforms/upduino_v1.py
migen/build/platforms/usrp_b100.py
migen/build/platforms/versa.py
