Metadata-Version: 2.1
Name: migen
Version: 0.9.1
Summary: Python toolbox for building complex digital hardware
Home-page: https://m-labs.hk
Author: Sebastien Bourdeauducq
Author-email: sb@m-labs.hk
License: BSD
Download-URL: https://github.com/m-labs/migen
Keywords: HDL ASIC FPGA hardware design
Platform: Any
Classifier: Topic :: Scientific/Engineering :: Electronic Design Automation (EDA)
Classifier: Environment :: Console
Classifier: Development Status :: 4 - Beta
Classifier: Intended Audience :: Developers
Classifier: License :: OSI Approved :: BSD License
Classifier: Operating System :: OS Independent
Classifier: Programming Language :: Python
Classifier: Programming Language :: Python :: 3.3
Classifier: Programming Language :: Python :: 3.4
Classifier: Programming Language :: Python :: 3.5
Classifier: Programming Language :: Python :: 3.6
Classifier: Programming Language :: Python :: 3.7
